firefly_ynab4_importer/__init__.py
firefly_ynab4_importer/main.py
Firefly_YNAB4_Importer-0.3.1.dist-info/LICENSE
Firefly_YNAB4_Importer-0.3.1.dist-info/METADATA
Firefly_YNAB4_Importer-0.3.1.dist-info/WHEEL
Firefly_YNAB4_Importer-0.3.1.dist-info/entry_points.txt
Firefly_YNAB4_Importer-0.3.1.dist-info/top_level.txt
Firefly_YNAB4_Importer-0.3.1.dist-info/RECORD
