Metadata-Version: 2.1
Name: Firefly-YNAB4-Importer
Version: 0.3.1
Summary: Firefly iii Importer from YNAB 4
Home-page: https://github.com/maroux/Firefly-YNAB4-Importer
Author: Aniruddha Maru
Maintainer: Aniruddha Maru
Maintainer-email: aniruddhamaru@gmail.com
License: MIT
Keywords: ynab ynab4 firefly fireflyiii
Platform: UNKNOWN
Classifier: Natural Language :: English
Classifier: Development Status :: 4 - Beta
Classifier: Intended Audience :: End Users/Desktop
Classifier: Topic :: Office/Business :: Financial :: Accounting
Classifier: Programming Language :: Python
Classifier: Programming Language :: Python :: 3.8
Classifier: License :: OSI Approved :: MIT License
Requires-Python: >=3.8
Requires-Dist: arrow
Requires-Dist: dacite
Requires-Dist: funcy
Requires-Dist: requests[security]
Requires-Dist: toml
Requires-Dist: click
Requires-Dist: Colorama
Provides-Extra: dev
Requires-Dist: flake8 ; extra == 'dev'
Requires-Dist: mypy ; extra == 'dev'
Requires-Dist: ipdb ; extra == 'dev'
Provides-Extra: publish
Requires-Dist: wheel ; extra == 'publish'
Requires-Dist: bumpversion ; extra == 'publish'
Requires-Dist: twine ; extra == 'publish'
Provides-Extra: test
Requires-Dist: pytest ; extra == 'test'
Requires-Dist: flake8 ; extra == 'test'
Requires-Dist: mypy ; extra == 'test'
Requires-Dist: pytest-env ; extra == 'test'
Requires-Dist: ipdb ; extra == 'test'
Requires-Dist: coverage ; extra == 'test'
Requires-Dist: pytest-cov ; extra == 'test'
Requires-Dist: black ; extra == 'test'
